odoo/addons/sale_commercial_partner/README.rst
odoo/addons/sale_commercial_partner/__init__.py
odoo/addons/sale_commercial_partner/__manifest__.py
odoo/addons/sale_commercial_partner/i18n/ca_ES.po
odoo/addons/sale_commercial_partner/i18n/de.po
odoo/addons/sale_commercial_partner/i18n/el_GR.po
odoo/addons/sale_commercial_partner/i18n/es.po
odoo/addons/sale_commercial_partner/i18n/es_VE.po
odoo/addons/sale_commercial_partner/i18n/fi.po
odoo/addons/sale_commercial_partner/i18n/fr.po
odoo/addons/sale_commercial_partner/i18n/hr.po
odoo/addons/sale_commercial_partner/i18n/hu.po
odoo/addons/sale_commercial_partner/i18n/it.po
odoo/addons/sale_commercial_partner/i18n/nl.po
odoo/addons/sale_commercial_partner/i18n/pt_BR.po
odoo/addons/sale_commercial_partner/i18n/ro.po
odoo/addons/sale_commercial_partner/i18n/sale_commercial_partner.pot
odoo/addons/sale_commercial_partner/i18n/sl_SI.po
odoo/addons/sale_commercial_partner/i18n/tr.po
odoo/addons/sale_commercial_partner/i18n/vi_VN.po
odoo/addons/sale_commercial_partner/i18n/zh_CN.po
odoo/addons/sale_commercial_partner/models/__init__.py
odoo/addons/sale_commercial_partner/models/sale.py
odoo/addons/sale_commercial_partner/readme/CONTRIBUTORS.rst
odoo/addons/sale_commercial_partner/readme/DESCRIPTION.rst
odoo/addons/sale_commercial_partner/readme/USAGE.rst
odoo/addons/sale_commercial_partner/static/description/icon.png
odoo/addons/sale_commercial_partner/static/description/index.html
odoo/addons/sale_commercial_partner/views/sale_views.xml
odoo13_addon_sale_commercial_partner-13.0.1.0.1.dev8.dist-info/METADATA
odoo13_addon_sale_commercial_partner-13.0.1.0.1.dev8.dist-info/WHEEL
odoo13_addon_sale_commercial_partner-13.0.1.0.1.dev8.dist-info/top_level.txt
odoo13_addon_sale_commercial_partner-13.0.1.0.1.dev8.dist-info/RECORD
